{
  "Name": "Customer",
  "Description": "Returns the information of a Customer record in JSON object format",
  "HttpMethod": "GET",
  "IsEnabled": true,
  "OrderIndex": 7,
  "CrossDomainPolicy": "PortalAliasesOnly",
  "Input": [
    {
      "Name": "RecordId",
      "IsDeleted": false,
      "IsEnabled": true,
      "OrderIndex": 0,
      "Parameters": {},
      "InputTypeStr": "text",
      "Validations": [
        {
          "Data": "{\"Message\":\"RecordId is required.\"}",
          "Type": "default-required",
          "IsDeleted": false,
          "IsEnabled": false,
          "OrderIndex": 0,
          "Metadata": {
            "PAP_InternalIdentifier": "Api.InputField.RequiredValidator"
          }
        }
      ]
    }
  ],
  "Actions": [
    {
      "ActionType": "PlantAnApp.ReadEntity.c1ba9698-71c8-416c-b7ca-6d30e7cbd2f6",
      "OrderIndex": 0,
      "Parameters": {
        "RecordId": "[RecordId]",
        "OutputToken": "Record"
      },
      "IsDisabled": false,
      "ExecutionType": "OnExecute",
      "Metadata": {
        "PAP_InternalIdentifier": "Api.ReadEntity",
        "EntityIdentifier": "c1ba9698-71c8-416c-b7ca-6d30e7cbd2f6",
        "IsUidEnabled": "True"
      }
    },
    {
      "ActionType": "JsonObject",
      "OrderIndex": 1,
      "Parameters": {
        "HttpCode": "200 OK",
        "Fields": [
          {
            "name": "Id",
            "value": "[RecordId]"
          },
          {
            "name": "Name",
            "value": "[Record:Name]"
          },
          {
            "name": "EmailAddress",
            "value": "[Record:EmailAddress]"
          },
          {
            "name": "MobilePhone",
            "value": "[Record:MobilePhone]"
          },
          {
            "name": "IsActive",
            "value": "[Record:IsActive]"
          },
          {
            "name": "StartDate",
            "value": "[Record:StartDate]"
          }
        ],
        "Headers": []
      },
      "IsDisabled": false,
      "ExecutionType": "OnExecute",
      "Metadata": {
        "PAP_InternalIdentifier": "Api.Response"
      }
    }
  ],
  "OnErrorActions": []
}